music_manager_micro/__init__.py
music_manager_micro/_database.py
music_manager_micro/_file.py
music_manager_micro/music_manager.py
music_manager_micro-0.3.4.dist-info/METADATA
music_manager_micro-0.3.4.dist-info/WHEEL
music_manager_micro-0.3.4.dist-info/licenses/LICENSE
music_manager_micro-0.3.4.dist-info/RECORD
