Metadata-Version: 2.1
Name: music_manager_micro
Version: 0.3.4
Summary: A media file discovery tool, intended to work alone or fit into a larger toolchain
Author: Samuel Shiels
License-File: LICENSE
Classifier: Development Status :: 3 - Alpha
Classifier: Environment :: Other Environment
Classifier: Intended Audience :: System Administrators
Classifier: License :: OSI Approved :: MIT License
Classifier: Operating System :: POSIX :: Linux
Classifier: Programming Language :: Python :: 3
Classifier: Topic :: Multimedia :: Sound/Audio
Classifier: Topic :: Utilities
Requires-Python: >=3.11.5
Requires-Dist: jsonpickle
